[
    {
        "name": "orangeBall",
        "type": "ball",
        "colorLowerBound": [
            0,
            107,
            155
        ],
        "colorUpperBound": [
            31,
            218,
            255
        ]
    },
    {
        "name": "whiteBall",
        "type": "ball",
        "colorLowerBound": [
            0,
            21,
            155
        ],
        "colorUpperBound": [
            28,
            138,
            255
        ]
    },
    {
        "name": "obstacle",
        "type": "obstacle",
        "colorLowerBound": [
            134,
            119,
            11
        ],
        "colorUpperBound": [
            161,
            255,
            244
        ]
    }
]